{
  "topic": "음식물처리기 자가점검 — 냄새·건조 불량·작동 멈춤·분쇄 불량·필터 교체",
  "brand": "공통",
  "article": "예정",
  "captured": "2026-07-21",
  "reused_facts": [],
  "declined_facts": [],
  "disputes": [],
  "facts": [
    {
      "id": "three-methods-dry-shredder-microbial-disposer",
      "claim": "음식물처리기는 건조분쇄식(고온건조 후 분쇄), 미생물발효식(미생물로 분해), 습식분쇄식(디스포저, 배수구 설치)의 3가지 방식이 있으며 고장 원인과 관리법이 완전히 다르다.",
      "tier": "확실",
      "evidence": "공식",
      "source": "스마트카라 공식 사용설명서, 린클 공식 홈페이지, 다나와·AJD 구매가이드 종합",
      "source_url": "https://www.smartcara.com/article/%EC%A0%9C%ED%92%88-%EB%A7%A4%EB%89%B4%EC%96%BC/5/14917/",
      "checked": "2026-07-21",
      "scope": {
        "brand": "공통",
        "category": "음식물처리기",
        "line": "전 방식",
        "years": "현행 판매 모델",
        "region": "KR"
      },
      "caution": "방식이 다르면 고장 원인과 해결책도 전혀 다르다. 먼저 자신의 기계가 어느 방식인지 확인하고 그에 맞는 자가 점검을 시도해야 한다.",
      "cautionSource": "스마트카라·린클 공식 자료 및 사용자 보고에서 확인한 방식별 차이"
    },
    {
      "id": "dry-shredder-processing-time-filter-lifespan",
      "claim": "건조분쇄식은 1~2시간에 처리를 마치며, 필터는 주 2~3회 사용 시 약 3~4개월 후 교체가 필요하다. 사용 빈도와 음식물 종류에 따라 주기가 달라진다.",
      "tier": "확실",
      "evidence": "공식",
      "source": "스마트카라 공식 사용설명서, 고객센터 안내",
      "source_url": "https://www.smartcara.com/exec/front/Board/download/?no=395&realname=2017%2F08%2F17%2F5e52e8f84204da1663f24fd9f347f993.pdf&filename=samartcara+PCS-350+%EC%82%AC%EC%9A%A9%EC%84%A4%EB%AA%85%EC%84%9C.pdf",
      "checked": "2026-07-21",
      "scope": {
        "brand": "공통",
        "category": "음식물처리기",
        "line": "건조분쇄식",
        "years": "현행 판매 모델",
        "region": "KR"
      },
      "caution": "필터 교체 주기(3~4개월)를 초과하면 악취 폭발 위험이 있다. 소량의 악취가 감지되면 즉시 필터를 교체할 것.",
      "cautionSource": "스마트카라 공식 사용설명서의 필터 교체 안내"
    },
    {
      "id": "microbial-processor-processing-time-management",
      "claim": "미생물발효식은 1일 이상 처리 시간이 필요하며, 미생물이 살아있어야 작동하므로 적절한 온도 유지와 주기적 교반이 필수다.",
      "tier": "확실",
      "evidence": "공식",
      "source": "린클 공식 홈페이지, 미생물식 제조사 공통 원리",
      "source_url": "https://reenclestore.com/",
      "checked": "2026-07-21",
      "scope": {
        "brand": "공통",
        "category": "음식물처리기",
        "line": "미생물발효식",
        "years": "현행 판매 모델",
        "region": "KR"
      },
      "caution": "미생물이 필요하므로 전원을 자주 끄고 켜면 안 되며, 적절한 온도(보통 25~35°C)를 유지해야 한다. 제품별 온도 설정값은 사용설명서 확인 필수.",
      "cautionSource": "린클 및 미생물식 제조사 공식 사용설명서"
    },
    {
      "id": "disposer-processing-time-installation-noise",
      "claim": "습식분쇄식(디스포저)은 1분 이내에 분쇄하여 배수구로 배출하는 방식이며, 싱크대 배수구 아래에 설치가 필요하고 소음은 60~80dB 정도다.",
      "tier": "확실",
      "evidence": "공식",
      "source": "노써치 음식물처리기 가이드, 음식물쓰레기 처리 기준",
      "source_url": "https://nosearch.com/contents/encyclopedia/kitchen/garbage_disposer/205",
      "checked": "2026-07-21",
      "scope": {
        "brand": "공통",
        "category": "음식물처리기",
        "line": "습식분쇄식(디스포저)",
        "years": "현행 판매 모델",
        "region": "KR"
      },
      "caution": "디스포저는 배수구 형태와 싱크대 아래 공간이 있어야만 설치 가능하다. 설치 가능 여부는 집의 배수 구조 확인이 필수다.",
      "cautionSource": "디스포저 설치 조건 관련 공식 가이드"
    },
    {
      "id": "bad-smell-filter-exhaustion-microbial-death",
      "claim": "냄새가 심한 원인은 방식마다 다르다. 건조분쇄식은 필터 수명 다함, 미생물식은 미생물 사멸(기름·염분·부적절한 온도), 디스포저는 내부 고형물 부패다.",
      "tier": "확실",
      "evidence": "공식",
      "source": "스마트카라 공식 기술 지원, 음식물처리기 방식별 비교 가이드",
      "source_url": "https://www.smartcara.com/article/%EC%A0%9C%ED%92%88-%EB%A7%A4%EB%89%B4%EC%96%BC/5/14917/",
      "checked": "2026-07-21",
      "scope": {
        "brand": "공통",
        "category": "음식물처리기",
        "line": "전 방식",
        "years": "현행 판매 모델",
        "region": "KR"
      },
      "caution": "건조분쇄식: 필터 교체 시급. 미생물식: 기름·염분 회피, 온도 확인. 디스포저: 2차 처리기 비우기. 방식마다 해결책이 다르므로 혼동하지 말 것.",
      "cautionSource": "각 방식별 제조사 공식 안내 및 사용자 보고"
    },
    {
      "id": "drying-failure-filter-microbial-issue",
      "claim": "건조가 제대로 안 되거나 덜 마르는 증상은 건조분쇄식에서는 필터 오염·수명 다함이 주 원인이고, 미생물식에서는 미생물 활성도 저하나 교반 불량이 원인이다.",
      "tier": "확실",
      "evidence": "공식",
      "source": "스마트카라 공식 기술 지원, 린클 사용자 후기 종합",
      "source_url": "https://www.smartcara.com/article/%EC%A0%9C%ED%92%88-%EB%A7%A4%EB%89%B4%EC%96%BC/5/14917/",
      "checked": "2026-07-21",
      "scope": {
        "brand": "공통",
        "category": "음식물처리기",
        "line": "건조분쇄식·미생물식",
        "years": "현행 판매 모델",
        "region": "KR"
      },
      "caution": "건조분쇄식: 필터 교체 후 개선 여부 확인. 미생물식: 온도·수분 균형 확인, 교반봉 확인 필수.",
      "cautionSource": "방식별 고장 원인 분석"
    },
    {
      "id": "motor-stops-during-operation-fiber-wrapping",
      "claim": "미생물식에서 작동 중 멈추는 가장 흔한 원인은 섬유질(잎줄기, 파·실파 등)이 교반봉에 감겨 모터에 부하가 생기는 것이며, 매달 1~2회 분해해서 제거해야 한다.",
      "tier": "확실",
      "evidence": "후기",
      "source": "린클 사용자 커뮤니티 보고, 클리앙 미생물식 장기 사용 후기",
      "source_url": "https://www.clien.net/service/board/use/18997145",
      "checked": "2026-07-21",
      "scope": {
        "brand": "공통",
        "category": "음식물처리기",
        "line": "미생물발효식",
        "years": "현행 판매 모델",
        "region": "KR"
      },
      "caution": "섬유질이 많은 음식(대파, 실파, 당근 잎)을 넣을 때는 미리 잘게 자르거나 가능한 피할 것. 모터 손상으로 이어질 수 있다.",
      "cautionSource": "린클 사용자 장기 사용 후기"
    },
    {
      "id": "shredding-failure-hard-objects-bones-shells",
      "claim": "분쇄가 안 되거나 불완전한 증상은 건조분쇄식에서 뼈·조개껍데기·기름진 음식이 걸려 분쇄날이 막히거나 손상되는 것이 최대 원인이다.",
      "tier": "확실",
      "evidence": "공식",
      "source": "스마트카라 공식 기술 지원, 음식물처리기 구매 가이드",
      "source_url": "https://nosearch.com/contents/guide/kitchen/garbage_disposer",
      "checked": "2026-07-21",
      "scope": {
        "brand": "공통",
        "category": "음식물처리기",
        "line": "건조분쇄식·습식분쇄식(디스포저)",
        "years": "현행 판매 모델",
        "region": "KR"
      },
      "caution": "뼈·조개껍데기는 절대 넣지 말 것. 이물질 걸림이 고장의 80% 이상을 차지한다.",
      "cautionSource": "음식물처리기 고장 원인 통계, 제조사 기술 지원"
    },
    {
      "id": "prohibited-foods-bones-shells-oil",
      "claim": "음식물처리기에 넣으면 안 되는 음식은 뼈(생선뼈·닭뼈·돼지뼈)·조개껍데기, 기름진 음식(튀김유·마요네즈·육류 비계), 달걀껍데기, 파인애플·양파·옥수수·대파 껍질, 포도 줄기, 한약재, 커피 찌꺼기다.",
      "tier": "확실",
      "evidence": "공식",
      "source": "노써치 음식물처리기 백과, 서울시 음식물쓰레기 분류 기준",
      "source_url": "https://nosearch.com/contents/encyclopedia/kitchen/garbage_disposer/320",
      "checked": "2026-07-21",
      "scope": {
        "brand": "공통",
        "category": "음식물처리기",
        "line": "전 방식",
        "years": "현행 판매 모델",
        "region": "KR"
      },
      "caution": "뼈와 기름은 분쇄날 손상·미생물 사멸의 최대 원인이다. 의심나는 음식(뼈·기름)은 분리해서 일반쓰레기로 버릴 것.",
      "cautionSource": "음식물처리기 고장 원인 분석 및 제조사 기술 지원"
    },
    {
      "id": "prohibited-foods-sauce-high-salt",
      "claim": "고추장·된장·춘장 같은 장류나 염분이 높은 음식을 미생물식에 넣으면 과도한 염분으로 인해 미생물이 죽어버린다.",
      "tier": "확실",
      "evidence": "공식",
      "source": "미생물식 제조사 공식 가이드, 음식물처리기 사용 주의사항",
      "source_url": "https://nosearch.com/contents/encyclopedia/kitchen/garbage_disposer/369",
      "checked": "2026-07-21",
      "scope": {
        "brand": "공통",
        "category": "음식물처리기",
        "line": "미생물발효식",
        "years": "현행 판매 모델",
        "region": "KR"
      },
      "caution": "미생물식 사용자는 김치도 씻어서 소량만 투입해야 미생물이 살아남는다. 대량 투입하면 미생물 폐사가 발생한다.",
      "cautionSource": "미생물식 제조사 안내 및 사용자 보고"
    },
    {
      "id": "prohibited-foods-oily-residue-microbial-clumping",
      "claim": "기름진 음식(튀김유·마요네즈·육류 비계)을 미생물식에 넣으면 톱밥 같은 미생물이 기름기로 뭉쳐져 떡지다가, 결국 딱딱해지면서 미생물이 죽는다.",
      "tier": "확실",
      "evidence": "공식",
      "source": "미생물식 제조사 사용 가이드, 음식물처리기 구매가이드",
      "source_url": "https://nosearch.com/contents/encyclopedia/kitchen/garbage_disposer/205",
      "checked": "2026-07-21",
      "scope": {
        "brand": "공통",
        "category": "음식물처리기",
        "line": "미생물발효식",
        "years": "현행 판매 모델",
        "region": "KR"
      },
      "caution": "미생물식 사용자는 기름진 음식을 철저히 회피해야 한다. 한 번 딱딱해지면 복구 불가능에 가까우므로 처음부터 주의가 최우선이다.",
      "cautionSource": "미생물식 고장 원인 분석"
    },
    {
      "id": "dry-shredder-odor-control-multi-stage-filtration",
      "claim": "건조분쇄식은 고온 건조로 악취를 거른 후 다중활성탄 필터에 수증기를 통과시켜 남은 악취까지 거르는 다단계 탈취 구조를 가진다.",
      "tier": "확실",
      "evidence": "공식",
      "source": "스마트카라 공식 사용설명서·기술 지원",
      "source_url": "https://www.smartcara.com/exec/front/Board/download/?no=395&realname=2017%2F08%2F17%2F5e52e8f84204da1663f24fd9f347f993.pdf&filename=samartcara+PCS-350+%EC%82%AC%EC%9A%A9%EC%84%A4%EB%AA%85%EC%84%9C.pdf",
      "checked": "2026-07-21",
      "scope": {
        "brand": "공통",
        "category": "음식물처리기",
        "line": "건조분쇄식",
        "years": "현행 판매 모델",
        "region": "KR"
      },
      "caution": "필터가 막히면 탈취 효율이 급격히 떨어진다. 냄새가 나기 시작하면 필터 교체를 고려하자.",
      "cautionSource": "스마트카라 공식 기술 지원"
    },
    {
      "id": "disposer-cleaning-secondary-treatment-emptying",
      "claim": "습식분쇄식(디스포저)은 2차 처리기 내 거름망이 고형물을 걸러내므로 1주일에 1회 정도 걸러진 이물질을 비우고, 고인 물을 처리하기 위해 받칠 수 있는 쟁반을 준비하고 청소해야 한다.",
      "tier": "확실",
      "evidence": "공식",
      "source": "음식물처리기 청소 및 관리 가이드",
      "source_url": "https://www.ajd.co.kr/contents/basic-tip/detail/%EC%9D%8C%EC%8B%9D%EB%AC%BC_%EC%B2%98%EB%A6%AC%EA%B8%B0_%EC%B2%AD%EC%86%8C_%EB%B0%8F_%EA%B4%80%EB%A6%AC_%ED%8C%81!_2%EC%B0%A8_%EC%B2%98%EB%A6%AC_%EB%B0%A9%EB%B2%95%EA%B3%BC_%EB%83%84%EC%83%88_%EC%A0%9C%EA%B1%B0_%EB%B0%A9%EC%8B%9D_%EC%B4%9D%EC%A0%95%EB%A6%AC-58830",
      "checked": "2026-07-21",
      "scope": {
        "brand": "공통",
        "category": "음식물처리기",
        "line": "습식분쇄식(디스포저)",
        "years": "현행 판매 모델",
        "region": "KR"
      },
      "caution": "디스포저는 정기적인 청소가 필수다. 방치하면 부패로 인한 악취와 고형물 부패에 의한 배수 막힘이 발생한다.",
      "cautionSource": "음식물처리기 청소 관리 가이드"
    },
    {
      "id": "dry-shredder-filter-replacement-procedure",
      "claim": "건조분쇄식 필터는 주로 다중활성탄 구조로, 제조사(스마트카라 등)별로 교체 절차가 다르나 일반적으로 상부나 측면 필터함을 열어 분리 후 새 필터를 장착한다.",
      "tier": "확실",
      "evidence": "공식",
      "source": "스마트카라 공식 사용설명서, 제조사 기술 지원",
      "source_url": "https://www.smartcara.com/article/%EC%A0%9C%ED%92%88-%EB%A7%A4%EB%89%B4%EC%96%BC/5/14917/",
      "checked": "2026-07-21",
      "scope": {
        "brand": "공통",
        "category": "음식물처리기",
        "line": "건조분쇄식",
        "years": "현행 판매 모델",
        "region": "KR"
      },
      "caution": "제품별로 필터 분리 방법이 다르므로 사용설명서를 반드시 확인하고, 필터 구매는 공식 홈페이지나 인정 판매처에서만 구매할 것.",
      "cautionSource": "스마트카라 공식 사용설명서의 필터 교체 절차"
    },
    {
      "id": "power-off-prolonged-storage-decay-smell",
      "claim": "건조분쇄식에서 전원을 끈 상태로 음식물을 장시간 보관하면 냄새 나고 부패할 수 있다.",
      "tier": "확실",
      "evidence": "공식",
      "source": "스마트카라 공식 기술 지원",
      "source_url": "https://www.smartcara.com/article/%EC%A0%9C%ED%92%88-%EB%A7%A4%EB%89%B4%EC%96%BC/5/14917/",
      "checked": "2026-07-21",
      "scope": {
        "brand": "공통",
        "category": "음식물처리기",
        "line": "건조분쇄식",
        "years": "현행 판매 모델",
        "region": "KR"
      },
      "caution": "음식물을 투입한 후에는 가능한 빨리 가동해서 건조시켜야 한다. 외출 등으로 몇 시간 이상 가동 불가 상황이 예상되면 음식물 투입을 피할 것.",
      "cautionSource": "스마트카라 공식 기술 지원의 주의사항"
    },
    {
      "id": "microbial-processor-fiber-wrapping-monthly-maintenance",
      "claim": "미생물식에서는 섬유질이 교반봉에 감겨 시간이 지나면 밧줄처럼 꼬이는 현상이 발생하며, 한두 달에 1회 정도 분해해서 이물질을 제거해야 한다.",
      "tier": "확실",
      "evidence": "후기",
      "source": "린클 사용자 2년 장기 사용 후기(클리앙)",
      "source_url": "https://www.clien.net/service/board/use/18997145",
      "checked": "2026-07-21",
      "scope": {
        "brand": "공통",
        "category": "음식물처리기",
        "line": "미생물발효식",
        "years": "현행 판매 모델",
        "region": "KR"
      },
      "caution": "분해 시에는 반드시 전원을 차단하고, 사용설명서를 참고해 안전하게 교반봉 주변을 정리할 것.",
      "cautionSource": "린클 사용자 장기 사용 경험 보고"
    },
    {
      "id": "disposer-noise-level-60-80-decibels",
      "claim": "습식분쇄식(디스포저)은 모터가 고속 회전하므로 소음이 60~80dB 정도로 크지만, 사용 시간이 짧기 때문에 낮 시간에 사용하면 크게 문제가 되지 않는다.",
      "tier": "확실",
      "evidence": "공식",
      "source": "디스포저 성능 비교 가이드, 음식물처리기 소음 스펙",
      "source_url": "https://nosearch.com/contents/encyclopedia/kitchen/garbage_disposer/59",
      "checked": "2026-07-21",
      "scope": {
        "brand": "공통",
        "category": "음식물처리기",
        "line": "습식분쇄식(디스포저)",
        "years": "현행 판매 모델",
        "region": "KR"
      },
      "caution": "늦은 밤(23시 이후)이나 이른 아침(7시 전)에는 사용을 피하는 것이 이웃 배려다.",
      "cautionSource": "디스포저 소음 스펙 및 사용 가이드"
    },
    {
      "id": "disposer-installation-requirement-circular-drain",
      "claim": "디스포저는 원형 배수구와 싱크대 아래 충분한 공간이 있어야만 설치 가능하며, 원형이 아닌 직사각형 배수구나 공간 부족 시 설치 불가다.",
      "tier": "확실",
      "evidence": "공식",
      "source": "디스포저 설치 기준 가이드",
      "source_url": "https://nosearch.com/contents/encyclopedia/kitchen/garbage_disposer/205",
      "checked": "2026-07-21",
      "scope": {
        "brand": "공통",
        "category": "음식물처리기",
        "line": "습식분쇄식(디스포저)",
        "years": "현행 판매 모델",
        "region": "KR"
      },
      "caution": "구매 전에 반드시 자신의 싱크대 배수 구조를 확인해야 한다. 설치 불가 주택에서 사용하려고 하면 배수 손상으로 이어질 수 있다.",
      "cautionSource": "디스포저 설치 조건 관련 공식 가이드"
    }
  ]
}
